nb_solution_remover/__init__.py
nb_solution_remover/main.py
nb_solution_remover-0.1.0.dist-info/METADATA
nb_solution_remover-0.1.0.dist-info/WHEEL
nb_solution_remover-0.1.0.dist-info/RECORD
