Metadata-Version: 2.1
Name: nb-solution-remover
Version: 0.1.0
Summary: 
Author: gazaboo
Author-email: florian.dadouchi@gmail.com
Requires-Python: >=3.11,<4.0
Classifier: Programming Language :: Python :: 3
Classifier: Programming Language :: Python :: 3.11
Classifier: Programming Language :: Python :: 3.12
Requires-Dist: nbformat (>=5.10.4,<6.0.0)
